PyQt5/bindings/QHexEdit/QHexEdit.sip
PyQt5/bindings/QHexEdit/QHexEdit.toml
QHexEdit.pyd
pyqt5_qhexedit-0.9.0.dist-info/WHEEL
pyqt5_qhexedit-0.9.0.dist-info/METADATA
pyqt5_qhexedit-0.9.0.dist-info/RECORD
